ninebot_ble/__init__.py
ninebot_ble/__main__.py
ninebot_ble/const.py
ninebot_ble/register.py
ninebot_ble/sensor.py
ninebot_ble/serial_parser.py
ninebot_ble/transport.py
ninebot_ble/util.py
ninebot_ble_jekson-0.1.0.dist-info/LICENSE
ninebot_ble_jekson-0.1.0.dist-info/METADATA
ninebot_ble_jekson-0.1.0.dist-info/WHEEL
ninebot_ble_jekson-0.1.0.dist-info/entry_points.txt
ninebot_ble_jekson-0.1.0.dist-info/top_level.txt
ninebot_ble_jekson-0.1.0.dist-info/RECORD
