Metadata-Version: 2.1
Name: ninebot-ble-jekson
Version: 0.1.0
Summary: Ninebot scooter BLE client
Author: ownbee
Project-URL: homepage, https://github.com/jekson/ninebot-ble
Classifier: Programming Language :: Python :: 3
Classifier: License :: OSI Approved :: MIT License
Classifier: Operating System :: OS Independent
Requires-Python: >=3.9
License-File: LICENSE
Requires-Dist: miauth ==0.9.7
Requires-Dist: bleak
Requires-Dist: bleak-retry-connector
Requires-Dist: bluetooth-sensor-state-data
Requires-Dist: bluetooth-data-tools
Provides-Extra: dev
Requires-Dist: black ; extra == 'dev'
Requires-Dist: mypy ; extra == 'dev'
